tech_tools/__init__.py
tech_tools/cli.py
tech_tools/detective_functions.py
tech_tools/multicast.py
tech_tools/resources.py
tech_tools/utilities.py
tech_tools/wireshark.py
tech_tools/files/mac.txt
tech_tools/files/wireshark.json
tech_tools/scripts/tech_tools_simple_script.py
tech_tools-0.4.dist-info/licenses/LICENSE
tech_tools-0.4.dist-info/METADATA
tech_tools-0.4.dist-info/WHEEL
tech_tools-0.4.dist-info/top_level.txt
tech_tools-0.4.dist-info/RECORD
