Metadata-Version: 2.4
Name: tech-tools
Version: 0.4
Summary: Basic Local Network Tools for Technicians
Author-email: Caleb Yourison <caleb.yourison@gmail.com>
License: MIT License
Project-URL: homepage, https://github.com/calebyourison/tech-tools
Keywords: networking,technician,cctv
Classifier: Development Status :: 3 - Alpha
Classifier: Programming Language :: Python :: 3
Requires-Python: >=3.8
License-File: LICENSE
Requires-Dist: pandas>=2.0.0
Dynamic: license-file
